Metadata-Version: 1.0
Name: image-converter
Version: 0.0.5
Summary: Let you convert any image size.
Home-page: https://github.com/SparrowJang/image_converter
Author: sparrow
Author-email: sprrow.jang@gmail.com
License: UNKNOWN
Keywords: image convert resize
Platform: UNKNOWN
